{
  "Name": "Talk161",
  "Blocks": [
    {
      "ItemID": 101,
      "Name": "Splash",
      "Description": "Splash",
      "Position": "(-2797.441,-1306.073)",
      "Commands": [
        {
          "ItemID": 279,
          "CmdType": "Fungus.TryinitFungaus"
        },
        {
          "ItemID": 166,
          "CmdType": "Fungus.CallMethod"
        },
        {
          "ItemID": 86,
          "CmdType": "Fungus.Call",
          "targetFlowchartName": null,
          "targetBlockID": "265(判断首次)",
          "startLabel": "",
          "startIndex": 0,
          "callMode": 0
        }
      ]
    },
    {
      "ItemID": 307,
      "Name": "错过提示",
      "Description": "错过提示",
      "Position": "(-2333.376,-1247.156)",
      "Commands": [
        {
          "ItemID": 322,
          "CmdType": "Fungus.SetStaticValue"
        },
        {
          "ItemID": 319,
          "CmdType": "Fungus.Say",
          "AvatarIDInt": 1,
          "AvatarBindKey": "",
          "StoryText": "糟糕，这次闭关的时间太久，这下可错过了和倪兄弟约定的时间了！",
          "Description": "",
          "AvatarIDSetType": "Normal"
        },
        {
          "ItemID": 320,
          "CmdType": "Fungus.Say",
          "AvatarIDInt": 2,
          "AvatarBindKey": "",
          "StoryText": "修真无日月，若是有{color=#d0380a}重要的事情{/color}要办，还是得在闭关时多留些心眼。",
          "Description": "",
          "AvatarIDSetType": "Normal"
        },
        {
          "ItemID": 321,
          "CmdType": "Fungus.Say",
          "AvatarIDInt": 2,
          "AvatarBindKey": "",
          "StoryText": "不过老夫记得你那小兄弟说过，自己是{color=#d0380a}武陵城{/color}中之人。去那里说不定还能找到他。",
          "Description": "",
          "AvatarIDSetType": "Normal"
        }
      ]
    },
    {
      "ItemID": 147,
      "Name": "New Block8",
      "Description": "New Block8",
      "Position": "(0,0)",
      "Commands": []
    },
    {
      "ItemID": 306,
      "Name": "无事发生",
      "Description": "无事发生",
      "Position": "(-2623.376,-1165.156)",
      "Commands": []
    },
    {
      "ItemID": 149,
      "Name": "New Block9",
      "Description": "New Block9",
      "Position": "(0,0)",
      "Commands": []
    },
    {
      "ItemID": 146,
      "Name": "New Block7",
      "Description": "New Block7",
      "Position": "(0,0)",
      "Commands": []
    },
    {
      "ItemID": 286,
      "Name": "错过二月判断",
      "Description": "错过二月判断",
      "Position": "(-2630.696,-1238.733)",
      "Commands": [
        {
          "ItemID": 301,
          "CmdType": "Fungus.GetNowTime"
        },
        {
          "ItemID": 302,
          "CmdType": "Fungus.If",
          "Condition": "month > 2"
        },
        {
          "ItemID": 303,
          "CmdType": "Fungus.GetStaticValue"
        },
        {
          "ItemID": 304,
          "CmdType": "Fungus.If",
          "Condition": "TempValue == 0"
        },
        {
          "ItemID": 308,
          "CmdType": "Fungus.Call",
          "targetFlowchartName": null,
          "targetBlockID": "305(首次对话判断)",
          "startLabel": "",
          "startIndex": 0,
          "callMode": 0
        },
        {
          "ItemID": 309,
          "CmdType": "Fungus.Else"
        },
        {
          "ItemID": 310,
          "CmdType": "Fungus.Call",
          "targetFlowchartName": null,
          "targetBlockID": "306(无事发生)",
          "startLabel": "",
          "startIndex": 0,
          "callMode": 0
        },
        {
          "ItemID": 325,
          "CmdType": "Fungus.End"
        },
        {
          "ItemID": 323,
          "CmdType": "Fungus.ElseIf",
          "Condition": "year > 1"
        },
        {
          "ItemID": 328,
          "CmdType": "Fungus.GetStaticValue"
        },
        {
          "ItemID": 329,
          "CmdType": "Fungus.If",
          "Condition": "TempValue == 0"
        },
        {
          "ItemID": 330,
          "CmdType": "Fungus.Call",
          "targetFlowchartName": null,
          "targetBlockID": "305(首次对话判断)",
          "startLabel": "",
          "startIndex": 0,
          "callMode": 0
        },
        {
          "ItemID": 331,
          "CmdType": "Fungus.Else"
        },
        {
          "ItemID": 332,
          "CmdType": "Fungus.Call",
          "targetFlowchartName": null,
          "targetBlockID": "306(无事发生)",
          "startLabel": "",
          "startIndex": 0,
          "callMode": 0
        },
        {
          "ItemID": 333,
          "CmdType": "Fungus.End"
        },
        {
          "ItemID": 313,
          "CmdType": "Fungus.Else"
        },
        {
          "ItemID": 312,
          "CmdType": "Fungus.Call",
          "targetFlowchartName": null,
          "targetBlockID": "306(无事发生)",
          "startLabel": "",
          "startIndex": 0,
          "callMode": 0
        }
      ]
    },
    {
      "ItemID": 265,
      "Name": "判断首次",
      "Description": "判断首次",
      "Position": "(-2798.06,-1242.532)",
      "Commands": [
        {
          "ItemID": 280,
          "CmdType": "Fungus.GetStaticValue"
        },
        {
          "ItemID": 282,
          "CmdType": "Fungus.CheckTime"
        },
        {
          "ItemID": 281,
          "CmdType": "Fungus.If",
          "Condition": "TempValue == 0"
        },
        {
          "ItemID": 283,
          "CmdType": "Fungus.If",
          "Condition": "Var == True"
        },
        {
          "ItemID": 284,
          "CmdType": "Fungus.Call",
          "targetFlowchartName": null,
          "targetBlockID": "285(首次对话)",
          "startLabel": "",
          "startIndex": 0,
          "callMode": 0
        },
        {
          "ItemID": 288,
          "CmdType": "Fungus.End"
        },
        {
          "ItemID": 287,
          "CmdType": "Fungus.Else"
        },
        {
          "ItemID": 289,
          "CmdType": "Fungus.Call",
          "targetFlowchartName": null,
          "targetBlockID": "286(错过二月判断)",
          "startLabel": "",
          "startIndex": 0,
          "callMode": 0
        }
      ]
    },
    {
      "ItemID": 305,
      "Name": "首次对话判断",
      "Description": "首次对话判断",
      "Position": "(-2484.376,-1243.156)",
      "Commands": [
        {
          "ItemID": 314,
          "CmdType": "Fungus.GetStaticValue"
        },
        {
          "ItemID": 315,
          "CmdType": "Fungus.If",
          "Condition": "TempValue == 0"
        },
        {
          "ItemID": 316,
          "CmdType": "Fungus.Call",
          "targetFlowchartName": null,
          "targetBlockID": "307(错过提示)",
          "startLabel": "",
          "startIndex": 0,
          "callMode": 0
        },
        {
          "ItemID": 317,
          "CmdType": "Fungus.Else"
        },
        {
          "ItemID": 318,
          "CmdType": "Fungus.Call",
          "targetFlowchartName": null,
          "targetBlockID": "306(无事发生)",
          "startLabel": "",
          "startIndex": 0,
          "callMode": 0
        }
      ]
    },
    {
      "ItemID": 285,
      "Name": "首次对话",
      "Description": "首次对话",
      "Position": "(-2795.304,-1175.877)",
      "Commands": [
        {
          "ItemID": 297,
          "CmdType": "Fungus.SetStaticValue"
        },
        {
          "ItemID": 294,
          "CmdType": "Fungus.Say",
          "AvatarIDInt": 2,
          "AvatarBindKey": "",
          "StoryText": "有意思，这客栈里还布下了一个小型的聚灵阵。",
          "Description": "",
          "AvatarIDSetType": "Normal"
        },
        {
          "ItemID": 293,
          "CmdType": "Fungus.Say",
          "AvatarIDInt": 1,
          "AvatarBindKey": "",
          "StoryText": "聚灵阵？那是什么？",
          "Description": "",
          "AvatarIDSetType": "Normal"
        },
        {
          "ItemID": 292,
          "CmdType": "Fungus.Say",
          "AvatarIDInt": 2,
          "AvatarBindKey": "",
          "StoryText": "聚灵阵是一种用灵石布下的基础阵法，可以慢慢地将周天的灵气汇聚集中起来，一般都是修真门派才有这样的手笔。",
          "Description": "",
          "AvatarIDSetType": "Normal"
        },
        {
          "ItemID": 291,
          "CmdType": "Fungus.Say",
          "AvatarIDInt": 2,
          "AvatarBindKey": "",
          "StoryText": "对于修真者来说，在一个灵气充裕的地方{color=#d0380a}闭关{/color}修炼，是可以事半功倍的。",
          "Description": "",
          "AvatarIDSetType": "Normal"
        },
        {
          "ItemID": 295,
          "CmdType": "Fungus.Say",
          "AvatarIDInt": 1,
          "AvatarBindKey": "",
          "StoryText": "但这租金……要是闭关个几年，那真是心疼啊……",
          "Description": "",
          "AvatarIDSetType": "Normal"
        },
        {
          "ItemID": 298,
          "CmdType": "Fungus.Say",
          "AvatarIDInt": 2,
          "AvatarBindKey": "",
          "StoryText": "舍不得身外钱财，还想逆天改命求长生？如此条件在这东石谷已经罕见了，快去租个房间开始修炼吧。",
          "Description": "",
          "AvatarIDSetType": "Normal"
        },
        {
          "ItemID": 299,
          "CmdType": "Fungus.Say",
          "AvatarIDInt": 1,
          "AvatarBindKey": "",
          "StoryText": "可我这一闭关，万一错过了{color=#d0380a}下个月{/color}和倪兄弟的约定，岂不误事？",
          "Description": "",
          "AvatarIDSetType": "Normal"
        },
        {
          "ItemID": 300,
          "CmdType": "Fungus.Say",
          "AvatarIDInt": 2,
          "AvatarBindKey": "",
          "StoryText": "看不出你这{xiaozi}还挺守信的，那就自己闭关时多留几个心眼，别错过了时日。",
          "Description": "",
          "AvatarIDSetType": "Normal"
        }
      ]
    }
  ],
  "Variables": []
}