{
  "Name": "Talk8",
  "Blocks": [
    {
      "ItemID": 96,
      "Name": "START",
      "Description": "START",
      "Position": "(-2795.746,-1225.58)",
      "Commands": [
        {
          "ItemID": 184,
          "CmdType": "Fungus.GetStaticValue"
        },
        {
          "ItemID": 185,
          "CmdType": "Fungus.If",
          "Condition": "TempValue == 2"
        },
        {
          "ItemID": 178,
          "CmdType": "Fungus.Say",
          "AvatarIDInt": 605,
          "AvatarBindKey": "",
          "StoryText": "你是之前那个什么...{FirstName}{LastName}吧？最近山上正缺人手，你{xiaozi}他妈的跑哪去了？",
          "Description": "",
          "AvatarIDSetType": "Normal"
        },
        {
          "ItemID": 183,
          "CmdType": "Fungus.Say",
          "AvatarIDInt": 605,
          "AvatarBindKey": "",
          "StoryText": "还好办正事儿之前你回来了，快点快点...还傻站着干什么呢？",
          "Description": "",
          "AvatarIDSetType": "Normal"
        },
        {
          "ItemID": 182,
          "CmdType": "Fungus.Say",
          "AvatarIDInt": 605,
          "AvatarBindKey": "",
          "StoryText": "快点跟我过来，大首领在山里边等着呢！",
          "Description": "",
          "AvatarIDSetType": "Normal"
        },
        {
          "ItemID": 189,
          "CmdType": "Fungus.Menu",
          "Text": "直接翻脸",
          "TargetBlockID": "this:188(直接翻脸)"
        },
        {
          "ItemID": 190,
          "CmdType": "Fungus.Menu",
          "Text": "假意应承",
          "TargetBlockID": "this:187(假意应承)"
        },
        {
          "ItemID": 263,
          "CmdType": "Fungus.ElseIf",
          "Condition": "TempValue == 3"
        },
        {
          "ItemID": 264,
          "CmdType": "Fungus.Call",
          "targetFlowchartName": null,
          "targetBlockID": null,
          "startLabel": "",
          "startIndex": 0,
          "callMode": 0
        },
        {
          "ItemID": 256,
          "CmdType": "Fungus.ElseIf",
          "Condition": "TempValue == 4"
        },
        {
          "ItemID": 257,
          "CmdType": "Fungus.Call",
          "targetFlowchartName": null,
          "targetBlockID": null,
          "startLabel": "",
          "startIndex": 0,
          "callMode": 0
        },
        {
          "ItemID": 261,
          "CmdType": "Fungus.ElseIf",
          "Condition": "TempValue == 5"
        },
        {
          "ItemID": 262,
          "CmdType": "Fungus.Call",
          "targetFlowchartName": null,
          "targetBlockID": null,
          "startLabel": "",
          "startIndex": 0,
          "callMode": 0
        },
        {
          "ItemID": 280,
          "CmdType": "Fungus.ElseIf",
          "Condition": "TempValue == 6"
        },
        {
          "ItemID": 281,
          "CmdType": "Fungus.Call",
          "targetFlowchartName": null,
          "targetBlockID": null,
          "startLabel": "",
          "startIndex": 0,
          "callMode": 0
        },
        {
          "ItemID": 186,
          "CmdType": "Fungus.Else"
        },
        {
          "ItemID": 269,
          "CmdType": "Fungus.GetStaticValue"
        },
        {
          "ItemID": 270,
          "CmdType": "Fungus.If",
          "Condition": "TempValue == 0"
        },
        {
          "ItemID": 224,
          "CmdType": "Fungus.GetStaticValue"
        },
        {
          "ItemID": 225,
          "CmdType": "Fungus.If",
          "Condition": "TempValue == 2"
        },
        {
          "ItemID": 268,
          "CmdType": "Fungus.SetStaticValue"
        },
        {
          "ItemID": 179,
          "CmdType": "Fungus.Say",
          "AvatarIDInt": 1,
          "AvatarBindKey": "",
          "StoryText": "也不知道他们还记不记得我先前假装沂山派修士的事...前面好像还有不少禾山道的修士。",
          "Description": "",
          "AvatarIDSetType": "Normal"
        },
        {
          "ItemID": 192,
          "CmdType": "Fungus.Menu",
          "Text": "敛息潜入",
          "TargetBlockID": "this:226(敛息潜入)"
        },
        {
          "ItemID": 191,
          "CmdType": "Fungus.Menu",
          "Text": "贸然闯入",
          "TargetBlockID": "this:227(贸然闯入)"
        },
        {
          "ItemID": 271,
          "CmdType": "Fungus.Else"
        },
        {
          "ItemID": 274,
          "CmdType": "Fungus.SetStaticValue"
        },
        {
          "ItemID": 240,
          "CmdType": "Fungus.Say",
          "AvatarIDInt": 1,
          "AvatarBindKey": "",
          "StoryText": "这禾山道真本事没多少，门内弟子倒是人数众多...",
          "Description": "",
          "AvatarIDSetType": "Normal"
        },
        {
          "ItemID": 241,
          "CmdType": "Fungus.Menu",
          "Text": "敛息潜入",
          "TargetBlockID": "this:226(敛息潜入)"
        },
        {
          "ItemID": 242,
          "CmdType": "Fungus.Menu",
          "Text": "贸然闯入",
          "TargetBlockID": "this:227(贸然闯入)"
        },
        {
          "ItemID": 255,
          "CmdType": "Fungus.End"
        },
        {
          "ItemID": 272,
          "CmdType": "Fungus.Else"
        },
        {
          "ItemID": 273,
          "CmdType": "Fungus.Call",
          "targetFlowchartName": null,
          "targetBlockID": null,
          "startLabel": "",
          "startIndex": 0,
          "callMode": 0
        }
      ]
    },
    {
      "ItemID": 101,
      "Name": "Splash",
      "Description": "Splash",
      "Position": "(-2796.441,-1525.073)",
      "Commands": [
        {
          "ItemID": 132,
          "CmdType": "Fungus.CallMethod"
        },
        {
          "ItemID": 166,
          "CmdType": "Fungus.CallMethod"
        },
        {
          "ItemID": 86,
          "CmdType": "Fungus.Call",
          "targetFlowchartName": null,
          "targetBlockID": "307(变量)",
          "startLabel": "",
          "startIndex": 0,
          "callMode": 0
        }
      ]
    },
    {
      "ItemID": 147,
      "Name": "New Block8",
      "Description": "New Block8",
      "Position": "(0,0)",
      "Commands": []
    },
    {
      "ItemID": 307,
      "Name": "变量",
      "Description": "变量",
      "Position": "(-2799.471,-1464.179)",
      "Commands": [
        {
          "ItemID": 309,
          "CmdType": "Fungus.GetStaticValue"
        },
        {
          "ItemID": 310,
          "CmdType": "Fungus.SetVariable"
        },
        {
          "ItemID": 693,
          "CmdType": "Fungus.GetStaticValue"
        },
        {
          "ItemID": 694,
          "CmdType": "Fungus.SetVariable"
        },
        {
          "ItemID": 560,
          "CmdType": "Fungus.SetVariable"
        },
        {
          "ItemID": 561,
          "CmdType": "Fungus.GetImportantNpcId"
        },
        {
          "ItemID": 562,
          "CmdType": "CmdSetJiaoHuNPC"
        },
        {
          "ItemID": 563,
          "CmdType": "CmdInitNPC"
        },
        {
          "ItemID": 576,
          "CmdType": "Fungus.SetVariable"
        },
        {
          "ItemID": 639,
          "CmdType": "Fungus.SetVariable"
        },
        {
          "ItemID": 640,
          "CmdType": "Fungus.GetImportantNpcId"
        },
        {
          "ItemID": 641,
          "CmdType": "CmdSetJiaoHuNPC"
        },
        {
          "ItemID": 642,
          "CmdType": "CmdInitNPC"
        },
        {
          "ItemID": 643,
          "CmdType": "Fungus.SetVariable"
        },
        {
          "ItemID": 706,
          "CmdType": "Fungus.If",
          "Condition": "变量240 > 0"
        },
        {
          "ItemID": 712,
          "CmdType": "Fungus.If",
          "Condition": "JinJie >= 7"
        },
        {
          "ItemID": 711,
          "CmdType": "Fungus.SetTaskIndexFinish"
        },
        {
          "ItemID": 708,
          "CmdType": "Fungus.End"
        },
        {
          "ItemID": 713,
          "CmdType": "Fungus.End"
        },
        {
          "ItemID": 308,
          "CmdType": "Fungus.Call",
          "targetFlowchartName": null,
          "targetBlockID": "275(修为)",
          "startLabel": "",
          "startIndex": 0,
          "callMode": 0
        }
      ]
    },
    {
      "ItemID": 312,
      "Name": "无事发生",
      "Description": "无事发生",
      "Position": "(-2974.471,-1395.179)",
      "Commands": [
        {
          "ItemID": 313,
          "CmdType": "Fungus.End"
        }
      ]
    },
    {
      "ItemID": 275,
      "Name": "修为",
      "Description": "修为",
      "Position": "(-2798.615,-1394.716)",
      "Commands": [
        {
          "ItemID": 277,
          "CmdType": "Fungus.If",
          "Condition": "JinJie > 6"
        },
        {
          "ItemID": 692,
          "CmdType": "Fungus.If",
          "Condition": "变量244 == 0"
        },
        {
          "ItemID": 304,
          "CmdType": "Fungus.If",
          "Condition": "变量240 == 2"
        },
        {
          "ItemID": 696,
          "CmdType": "Fungus.SetStaticValue"
        },
        {
          "ItemID": 311,
          "CmdType": "Fungus.Call",
          "targetFlowchartName": null,
          "targetBlockID": "302(杜老二)",
          "startLabel": "",
          "startIndex": 0,
          "callMode": 0
        },
        {
          "ItemID": 649,
          "CmdType": "Fungus.ElseIf",
          "Condition": "变量240 == 3"
        },
        {
          "ItemID": 697,
          "CmdType": "Fungus.SetStaticValue"
        },
        {
          "ItemID": 650,
          "CmdType": "Fungus.Call",
          "targetFlowchartName": null,
          "targetBlockID": "651(麻老九)",
          "startLabel": "",
          "startIndex": 0,
          "callMode": 0
        },
        {
          "ItemID": 305,
          "CmdType": "Fungus.Else"
        },
        {
          "ItemID": 276,
          "CmdType": "Fungus.Call",
          "targetFlowchartName": null,
          "targetBlockID": "96(START)",
          "startLabel": "",
          "startIndex": 0,
          "callMode": 0
        },
        {
          "ItemID": 306,
          "CmdType": "Fungus.End"
        },
        {
          "ItemID": 691,
          "CmdType": "Fungus.End"
        },
        {
          "ItemID": 278,
          "CmdType": "Fungus.Else"
        },
        {
          "ItemID": 279,
          "CmdType": "Fungus.Call",
          "targetFlowchartName": null,
          "targetBlockID": "312(无事发生)",
          "startLabel": "",
          "startIndex": 0,
          "callMode": 0
        }
      ]
    },
    {
      "ItemID": 226,
      "Name": "敛息潜入",
      "Description": "敛息潜入",
      "Position": "(-2970.615,-1299.989)",
      "Commands": [
        {
          "ItemID": 232,
          "CmdType": "Fungus.CheckStaticSkill"
        },
        {
          "ItemID": 233,
          "CmdType": "Fungus.If",
          "Condition": "Var1 == True"
        },
        {
          "ItemID": 234,
          "CmdType": "Fungus.Say",
          "AvatarIDInt": 0,
          "AvatarBindKey": "",
          "StoryText": "你运起敛息术跟上三五成群的禾山道修士，随着他们的脚步来到了幽谷。",
          "Description": "",
          "AvatarIDSetType": "FungusVariable"
        },
        {
          "ItemID": 282,
          "CmdType": "Fungus.SetSTalk"
        },
        {
          "ItemID": 245,
          "CmdType": "Fungus.LoadScene"
        },
        {
          "ItemID": 235,
          "CmdType": "Fungus.Else"
        },
        {
          "ItemID": 236,
          "CmdType": "Fungus.Say",
          "AvatarIDInt": 1,
          "AvatarBindKey": "",
          "StoryText": "我好像没学过敛息术...还是想想别的办法吧。",
          "Description": "",
          "AvatarIDSetType": "Normal"
        },
        {
          "ItemID": 238,
          "CmdType": "Fungus.Call",
          "targetFlowchartName": null,
          "targetBlockID": "237(选项)",
          "startLabel": "",
          "startIndex": 0,
          "callMode": 0
        }
      ]
    },
    {
      "ItemID": 217,
      "Name": "menu",
      "Description": "menu",
      "Position": "(-2628.615,-1226.716)",
      "Commands": [
        {
          "ItemID": 220,
          "CmdType": "Fungus.Say",
          "AvatarIDInt": 605,
          "AvatarBindKey": "",
          "StoryText": "{w}{w=0.5}你有什么要问的尽管开口！",
          "Description": "",
          "AvatarIDSetType": "Normal"
        },
        {
          "ItemID": 221,
          "CmdType": "Fungus.Menu",
          "Text": "要办什么正事",
          "TargetBlockID": "this:202(要办什么正事)"
        },
        {
          "ItemID": 222,
          "CmdType": "Fungus.Menu",
          "Text": "大首领最近如何",
          "TargetBlockID": "this:203(大首领最近如何)"
        },
        {
          "ItemID": 223,
          "CmdType": "Fungus.Menu",
          "Text": "没什么要问的了",
          "TargetBlockID": "this:204(没什么要问的了)"
        }
      ]
    },
    {
      "ItemID": 149,
      "Name": "New Block9",
      "Description": "New Block9",
      "Position": "(0,0)",
      "Commands": []
    },
    {
      "ItemID": 146,
      "Name": "New Block7",
      "Description": "New Block7",
      "Position": "(0,0)",
      "Commands": []
    },
    {
      "ItemID": 251,
      "Name": "还是算了",
      "Description": "还是算了",
      "Position": "(-3131.615,-1223.716)",
      "Commands": [
        {
          "ItemID": 259,
          "CmdType": "Fungus.SetStaticValue"
        },
        {
          "ItemID": 267,
          "CmdType": "Fungus.SetStaticValue"
        }
      ]
    },
    {
      "ItemID": 237,
      "Name": "选项",
      "Description": "选项",
      "Position": "(-2969.615,-1224.716)",
      "Commands": [
        {
          "ItemID": 249,
          "CmdType": "Fungus.Menu",
          "Text": "贸然闯入",
          "TargetBlockID": "this:227(贸然闯入)"
        },
        {
          "ItemID": 250,
          "CmdType": "Fungus.Menu",
          "Text": "还是算了",
          "TargetBlockID": "this:251(还是算了)"
        }
      ]
    },
    {
      "ItemID": 187,
      "Name": "假意应承",
      "Description": "假意应承",
      "Position": "(-2627.658,-1146.544)",
      "Commands": [
        {
          "ItemID": 195,
          "CmdType": "Fungus.Say",
          "AvatarIDInt": 1,
          "AvatarBindKey": "",
          "StoryText": "大哥见谅，我最近这不是出山搜罗供奉来了。你看，这是我在山下得到的，全都给大哥了。",
          "Description": "",
          "AvatarIDSetType": "Normal"
        },
        {
          "ItemID": 196,
          "CmdType": "Fungus.Say",
          "AvatarIDInt": 0,
          "AvatarBindKey": "",
          "StoryText": "你从储物袋里掏出一点灵石，对这种小门小派的修士来说这已经算是一笔巨财了。",
          "Description": "",
          "AvatarIDSetType": "FungusVariable"
        },
        {
          "ItemID": 197,
          "CmdType": "Fungus.Say",
          "AvatarIDInt": 0,
          "AvatarBindKey": "",
          "StoryText": "那禾山道修士见此变脸比翻书还快，一张臭脸登时笑出花来，乐呵呵地接下了你的灵石。",
          "Description": "",
          "AvatarIDSetType": "FungusVariable"
        },
        {
          "ItemID": 201,
          "CmdType": "Fungus.Say",
          "AvatarIDInt": 605,
          "AvatarBindKey": "",
          "StoryText": "好说，好说。",
          "Description": "",
          "AvatarIDSetType": "Normal"
        },
        {
          "ItemID": 200,
          "CmdType": "Fungus.Say",
          "AvatarIDInt": 605,
          "AvatarBindKey": "",
          "StoryText": "{w}{w=0.5}你有什么要问的尽管开口！",
          "Description": "",
          "AvatarIDSetType": "Normal"
        },
        {
          "ItemID": 207,
          "CmdType": "Fungus.Menu",
          "Text": "要办什么正事",
          "TargetBlockID": "this:202(要办什么正事)"
        },
        {
          "ItemID": 206,
          "CmdType": "Fungus.Menu",
          "Text": "大首领最近如何",
          "TargetBlockID": "this:203(大首领最近如何)"
        },
        {
          "ItemID": 205,
          "CmdType": "Fungus.Menu",
          "Text": "没什么要问的了",
          "TargetBlockID": "this:204(没什么要问的了)"
        }
      ]
    },
    {
      "ItemID": 202,
      "Name": "要办什么正事",
      "Description": "要办什么正事",
      "Position": "(-2794.658,-1146.544)",
      "Commands": [
        {
          "ItemID": 208,
          "CmdType": "Fungus.Say",
          "AvatarIDInt": 605,
          "AvatarBindKey": "",
          "StoryText": "前些日子大首领在山里发现了只妖兽，据说那妖丹服用后对修为有大裨益。这不，兄弟几个都被叫过来一起进山抓妖兽了，可惜那玩意儿跑得飞快，抓了月余连根毛都没捞着...",
          "Description": "",
          "AvatarIDSetType": "Normal"
        },
        {
          "ItemID": 209,
          "CmdType": "Fungus.Say",
          "AvatarIDInt": 605,
          "AvatarBindKey": "",
          "StoryText": "大首领气得不行，最后决定自己出马，我们负责把幽谷围住别让那猴子跑了就成。",
          "Description": "",
          "AvatarIDSetType": "Normal"
        },
        {
          "ItemID": 218,
          "CmdType": "Fungus.Call",
          "targetFlowchartName": null,
          "targetBlockID": "217(menu)",
          "startLabel": "",
          "startIndex": 0,
          "callMode": 0
        }
      ]
    },
    {
      "ItemID": 203,
      "Name": "大首领最近如何",
      "Description": "大首领最近如何",
      "Position": "(-2466.658,-1146.544)",
      "Commands": [
        {
          "ItemID": 213,
          "CmdType": "Fungus.Say",
          "AvatarIDInt": 605,
          "AvatarBindKey": "",
          "StoryText": "大首领最近有些焦躁，好像是遇到了瓶颈。",
          "Description": "",
          "AvatarIDSetType": "Normal"
        },
        {
          "ItemID": 214,
          "CmdType": "Fungus.Say",
          "AvatarIDInt": 605,
          "AvatarBindKey": "",
          "StoryText": "唉，要我说这境界不也挺好的，有什么着急的。金丹期...恐怕我这辈子都到不了喽。",
          "Description": "",
          "AvatarIDSetType": "Normal"
        },
        {
          "ItemID": 219,
          "CmdType": "Fungus.Call",
          "targetFlowchartName": null,
          "targetBlockID": "217(menu)",
          "startLabel": "",
          "startIndex": 0,
          "callMode": 0
        }
      ]
    },
    {
      "ItemID": 188,
      "Name": "直接翻脸",
      "Description": "直接翻脸",
      "Position": "(-2628.795,-1304.544)",
      "Commands": [
        {
          "ItemID": 193,
          "CmdType": "Fungus.Say",
          "AvatarIDInt": 0,
          "AvatarBindKey": "",
          "StoryText": "你上前一脚踹翻了禾山道修士，好歹你修练也小有所成，何必与这些炼气修士虚与委蛇。",
          "Description": "",
          "AvatarIDSetType": "FungusVariable"
        },
        {
          "ItemID": 194,
          "CmdType": "Fungus.Say",
          "AvatarIDInt": 0,
          "AvatarBindKey": "",
          "StoryText": "一旁的禾山道修士感受到你身上散发出的威压，吓得腿脚发软，跪地求饶。有几个修为高些的倒是率先反应过来，一溜烟跑进了幽谷，应当是去告知大首领了。",
          "Description": "",
          "AvatarIDSetType": "FungusVariable"
        },
        {
          "ItemID": 199,
          "CmdType": "Fungus.Say",
          "AvatarIDInt": 0,
          "AvatarBindKey": "",
          "StoryText": "你对禾山道知根知底，此地修为最高的也不过是那个血煞老怪，根本不足为惧。但他们聚集人手的目的还是令你有些在意，你决定前去幽谷一探究竟。",
          "Description": "",
          "AvatarIDSetType": "FungusVariable"
        },
        {
          "ItemID": 253,
          "CmdType": "Fungus.SetSTalk"
        },
        {
          "ItemID": 243,
          "CmdType": "Fungus.LoadScene"
        }
      ]
    },
    {
      "ItemID": 651,
      "Name": "麻老九",
      "Description": "麻老九",
      "Position": "(-2599.471,-1348.179)",
      "Commands": [
        {
          "ItemID": 698,
          "CmdType": "Fungus.Say",
          "AvatarIDInt": 0,
          "AvatarBindKey": "",
          "StoryText": "自从沂山双鬼死后，禾山派没了相互制衡的对象，变得愈发猖獗。",
          "Description": "",
          "AvatarIDSetType": "Normal"
        },
        {
          "ItemID": 699,
          "CmdType": "Fungus.Say",
          "AvatarIDInt": 0,
          "AvatarBindKey": "",
          "StoryText": "由于禾山派手段相较于沂山派更为残忍毒辣，所以周围百姓的处境反倒比之前更加艰难了。",
          "Description": "",
          "AvatarIDSetType": "Normal"
        },
        {
          "ItemID": 700,
          "CmdType": "Fungus.Say",
          "AvatarIDInt": 1,
          "AvatarBindKey": "",
          "StoryText": "“如今我已结丹，便来会会这颜老怪好了。”",
          "Description": "",
          "AvatarIDSetType": "Normal"
        },
        {
          "ItemID": 701,
          "CmdType": "Fungus.Say",
          "AvatarIDInt": 0,
          "AvatarBindKey": "",
          "StoryText": "禾山派前，只见许多三五成群的修士神色紧张地奔向山谷，口中还囔囔着“大首领”、“灵猴”的字眼，你便也跟了上去。",
          "Description": "",
          "AvatarIDSetType": "Normal"
        },
        {
          "ItemID": 704,
          "CmdType": "Fungus.SetStaticValue"
        },
        {
          "ItemID": 702,
          "CmdType": "Fungus.SetSTalk"
        },
        {
          "ItemID": 703,
          "CmdType": "Fungus.LoadScene"
        }
      ]
    },
    {
      "ItemID": 302,
      "Name": "杜老二",
      "Description": "杜老二",
      "Position": "(-2596.471,-1443.179)",
      "Commands": [
        {
          "ItemID": 652,
          "CmdType": "Fungus.If",
          "Condition": "杜老二境界 >= 7"
        },
        {
          "ItemID": 655,
          "CmdType": "Fungus.Say",
          "AvatarIDInt": 0,
          "AvatarBindKey": "",
          "StoryText": "刚到山脚，你便注意到不远处有一股与你实力相近的气息。",
          "Description": "",
          "AvatarIDSetType": "Normal"
        },
        {
          "ItemID": 657,
          "CmdType": "Fungus.Say",
          "AvatarIDInt": 0,
          "AvatarBindKey": "杜老二",
          "StoryText": "我还说是谁，原来是{xiongdi}你啊。",
          "Description": "",
          "AvatarIDSetType": "FungusVariable"
        },
        {
          "ItemID": 656,
          "CmdType": "Fungus.Say",
          "AvatarIDInt": 1,
          "AvatarBindKey": "",
          "StoryText": "杜兄？你怎么会在这？",
          "Description": "",
          "AvatarIDSetType": "Normal"
        },
        {
          "ItemID": 659,
          "CmdType": "Fungus.Say",
          "AvatarIDInt": 0,
          "AvatarBindKey": "杜老二",
          "StoryText": "结丹之后，我就经常站在这。",
          "Description": "",
          "AvatarIDSetType": "FungusVariable"
        },
        {
          "ItemID": 663,
          "CmdType": "Fungus.Say",
          "AvatarIDInt": 0,
          "AvatarBindKey": "杜老二",
          "StoryText": "我想就这么冲进去杀他娘的，但是我又打不过颜老怪，怕白亏了这身修为…",
          "Description": "",
          "AvatarIDSetType": "FungusVariable"
        },
        {
          "ItemID": 661,
          "CmdType": "Fungus.Say",
          "AvatarIDInt": 1,
          "AvatarBindKey": "",
          "StoryText": "或许趁他不备之时偷袭于他，会有奇效？",
          "Description": "",
          "AvatarIDSetType": "Normal"
        },
        {
          "ItemID": 660,
          "CmdType": "Fungus.Say",
          "AvatarIDInt": 0,
          "AvatarBindKey": "",
          "StoryText": "他摇了摇头。",
          "Description": "",
          "AvatarIDSetType": "Normal"
        },
        {
          "ItemID": 662,
          "CmdType": "Fungus.Say",
          "AvatarIDInt": 0,
          "AvatarBindKey": "杜老二",
          "StoryText": "偷袭解不了我心中的恨。只有从正门杀进去，我才觉得痛快！",
          "Description": "",
          "AvatarIDSetType": "FungusVariable"
        },
        {
          "ItemID": 664,
          "CmdType": "Fungus.Say",
          "AvatarIDInt": 1,
          "AvatarBindKey": "",
          "StoryText": "好一个从正门杀进去，那我便陪你走一遭罢。",
          "Description": "",
          "AvatarIDSetType": "Normal"
        },
        {
          "ItemID": 666,
          "CmdType": "Fungus.Say",
          "AvatarIDInt": 0,
          "AvatarBindKey": "杜老二",
          "StoryText": "你愿意帮我？",
          "Description": "",
          "AvatarIDSetType": "FungusVariable"
        },
        {
          "ItemID": 667,
          "CmdType": "Fungus.Say",
          "AvatarIDInt": 1,
          "AvatarBindKey": "",
          "StoryText": "禾山派为祸一方，若不是此前实力不足，我早就将其铲除了。",
          "Description": "",
          "AvatarIDSetType": "Normal"
        },
        {
          "ItemID": 668,
          "CmdType": "Fungus.Say",
          "AvatarIDInt": 0,
          "AvatarBindKey": "杜老二",
          "StoryText": "好！还是{xiongdi}你仗义！",
          "Description": "",
          "AvatarIDSetType": "FungusVariable"
        },
        {
          "ItemID": 665,
          "CmdType": "Fungus.Say",
          "AvatarIDInt": 0,
          "AvatarBindKey": "",
          "StoryText": "言罢，你二人便直接从正门走进了禾山道。",
          "Description": "",
          "AvatarIDSetType": "Normal"
        },
        {
          "ItemID": 705,
          "CmdType": "Fungus.SetStaticValue"
        },
        {
          "ItemID": 674,
          "CmdType": "Fungus.LoadScene"
        },
        {
          "ItemID": 653,
          "CmdType": "Fungus.Else"
        },
        {
          "ItemID": 676,
          "CmdType": "Fungus.Say",
          "AvatarIDInt": 0,
          "AvatarBindKey": "",
          "StoryText": "自从沂山双鬼死后，禾山派没了相互制衡的对象，变得愈发猖獗。",
          "Description": "",
          "AvatarIDSetType": "Normal"
        },
        {
          "ItemID": 688,
          "CmdType": "Fungus.Say",
          "AvatarIDInt": 0,
          "AvatarBindKey": "",
          "StoryText": "由于禾山派手段相较于沂山派更为残忍毒辣，所以周围百姓的处境反倒比之前更加艰难了。",
          "Description": "",
          "AvatarIDSetType": "Normal"
        },
        {
          "ItemID": 677,
          "CmdType": "Fungus.Say",
          "AvatarIDInt": 1,
          "AvatarBindKey": "",
          "StoryText": "“如今我已结丹，便来会会这颜老怪好了。”",
          "Description": "",
          "AvatarIDSetType": "Normal"
        },
        {
          "ItemID": 679,
          "CmdType": "Fungus.Say",
          "AvatarIDInt": 0,
          "AvatarBindKey": "",
          "StoryText": "禾山派前，只见许多三五成群的修士神色紧张地奔向山谷，口中还囔囔着“大首领”、“灵猴”的字眼，你便也跟了上去。",
          "Description": "",
          "AvatarIDSetType": "Normal"
        },
        {
          "ItemID": 689,
          "CmdType": "Fungus.SetSTalk"
        },
        {
          "ItemID": 690,
          "CmdType": "Fungus.LoadScene"
        }
      ]
    },
    {
      "ItemID": 204,
      "Name": "没什么要问的了",
      "Description": "没什么要问的了",
      "Position": "(-2630.658,-1065.544)",
      "Commands": [
        {
          "ItemID": 246,
          "CmdType": "Fungus.Say",
          "AvatarIDInt": 605,
          "AvatarBindKey": "",
          "StoryText": "既然你都知道了，那赶紧跟我去幽谷守着吧。",
          "Description": "",
          "AvatarIDSetType": "Normal"
        },
        {
          "ItemID": 260,
          "CmdType": "Fungus.SetSTalk"
        },
        {
          "ItemID": 247,
          "CmdType": "Fungus.LoadScene"
        }
      ]
    },
    {
      "ItemID": 227,
      "Name": "贸然闯入",
      "Description": "贸然闯入",
      "Position": "(-2970.615,-1146.716)",
      "Commands": [
        {
          "ItemID": 228,
          "CmdType": "Fungus.Say",
          "AvatarIDInt": 0,
          "AvatarBindKey": "",
          "StoryText": "你光明正大地从山门走进禾山道大本营，丝毫不掩饰自己的修为。",
          "Description": "",
          "AvatarIDSetType": "FungusVariable"
        },
        {
          "ItemID": 231,
          "CmdType": "Fungus.Say",
          "AvatarIDInt": 0,
          "AvatarBindKey": "",
          "StoryText": "一旁的禾山道修士感受到你身上散发出的威压，吓得腿脚发软，跪地求饶。有几个修为高些的倒是率先反应过来，一溜烟跑进了幽谷，应当是去告知大首领了。",
          "Description": "",
          "AvatarIDSetType": "FungusVariable"
        },
        {
          "ItemID": 230,
          "CmdType": "Fungus.Say",
          "AvatarIDInt": 0,
          "AvatarBindKey": "",
          "StoryText": "你对禾山道知根知底，此地修为最高的也不过是那个血煞老怪，根本不足为惧。但他们聚集人手的目的还是令你有些在意，你决定前去幽谷一探究竟。",
          "Description": "",
          "AvatarIDSetType": "FungusVariable"
        },
        {
          "ItemID": 254,
          "CmdType": "Fungus.SetSTalk"
        },
        {
          "ItemID": 244,
          "CmdType": "Fungus.LoadScene"
        }
      ]
    },
    {
      "ItemID": 285,
      "Name": "模板",
      "Description": "模板",
      "Position": "(-2589.471,-1523.179)",
      "Commands": [
        {
          "ItemID": 284,
          "CmdType": "Fungus.Say",
          "AvatarIDInt": 0,
          "AvatarBindKey": "",
          "StoryText": "旁白",
          "Description": "",
          "AvatarIDSetType": "Normal"
        },
        {
          "ItemID": 303,
          "CmdType": "Fungus.Say",
          "AvatarIDInt": 1,
          "AvatarBindKey": "",
          "StoryText": "主角",
          "Description": "",
          "AvatarIDSetType": "Normal"
        },
        {
          "ItemID": 286,
          "CmdType": "Fungus.Say",
          "AvatarIDInt": 0,
          "AvatarBindKey": "杜老二",
          "StoryText": "杜老二",
          "Description": "",
          "AvatarIDSetType": "FungusVariable"
        },
        {
          "ItemID": 288,
          "CmdType": "Fungus.Say",
          "AvatarIDInt": 0,
          "AvatarBindKey": "麻老九",
          "StoryText": "麻老九",
          "Description": "",
          "AvatarIDSetType": "FungusVariable"
        },
        {
          "ItemID": 287,
          "CmdType": "Fungus.Say",
          "AvatarIDInt": 0,
          "AvatarBindKey": "",
          "StoryText": "颜老怪",
          "Description": "",
          "AvatarIDSetType": "FungusVariable"
        },
        {
          "ItemID": 289,
          "CmdType": "Fungus.Call",
          "targetFlowchartName": null,
          "targetBlockID": null,
          "startLabel": "",
          "startIndex": 0,
          "callMode": 0
        },
        {
          "ItemID": 290,
          "CmdType": "Fungus.GetStaticValue"
        },
        {
          "ItemID": 291,
          "CmdType": "Fungus.SetVariable"
        },
        {
          "ItemID": 292,
          "CmdType": "Fungus.GetImportantNpcId"
        },
        {
          "ItemID": 293,
          "CmdType": "CmdSetJiaoHuNPC"
        },
        {
          "ItemID": 294,
          "CmdType": "CmdInitNPC"
        },
        {
          "ItemID": 295,
          "CmdType": "Fungus.If",
          "Condition": "Error: No variable selected"
        },
        {
          "ItemID": 296,
          "CmdType": "Fungus.Else"
        },
        {
          "ItemID": 297,
          "CmdType": "Fungus.End"
        },
        {
          "ItemID": 298,
          "CmdType": "Fungus.Menu",
          "Text": "Option Text",
          "TargetBlockID": ""
        },
        {
          "ItemID": 299,
          "CmdType": "Fungus.SetSTalk"
        },
        {
          "ItemID": 300,
          "CmdType": "Fungus.StartFight"
        },
        {
          "ItemID": 695,
          "CmdType": "Fungus.SetStaticValue"
        },
        {
          "ItemID": 301,
          "CmdType": "Fungus.CheckNpcDeath"
        },
        {
          "ItemID": 673,
          "CmdType": "Fungus.LoadScene"
        }
      ]
    }
  ],
  "Variables": []
}