{
  "Name": "Talk129103",
  "Blocks": [
    {
      "ItemID": 101,
      "Name": "Splash",
      "Description": "Splash",
      "Position": "(-2797.441,-1306.073)",
      "Commands": [
        {
          "ItemID": 279,
          "CmdType": "Fungus.TryinitFungaus"
        },
        {
          "ItemID": 166,
          "CmdType": "Fungus.CallMethod"
        },
        {
          "ItemID": 86,
          "CmdType": "Fungus.Call",
          "targetFlowchartName": null,
          "targetBlockID": "280(New Block)",
          "startLabel": "",
          "startIndex": 0,
          "callMode": 0
        }
      ]
    },
    {
      "ItemID": 147,
      "Name": "New Block8",
      "Description": "New Block8",
      "Position": "(0,0)",
      "Commands": []
    },
    {
      "ItemID": 149,
      "Name": "New Block9",
      "Description": "New Block9",
      "Position": "(0,0)",
      "Commands": []
    },
    {
      "ItemID": 146,
      "Name": "New Block7",
      "Description": "New Block7",
      "Position": "(0,0)",
      "Commands": []
    },
    {
      "ItemID": 283,
      "Name": "围墙",
      "Description": "围墙",
      "Position": "(-2894.694,-1136.018)",
      "Commands": [
        {
          "ItemID": 285,
          "CmdType": "Fungus.Say",
          "AvatarIDInt": 1020,
          "AvatarBindKey": "",
          "StoryText": "这广陵城有内外两道围墙，内墙有阵法加持，所以相对安全不少。",
          "Description": "",
          "AvatarIDSetType": "Normal"
        },
        {
          "ItemID": 286,
          "CmdType": "Fungus.Say",
          "AvatarIDInt": 1020,
          "AvatarBindKey": "",
          "StoryText": "外墙就危险多了，听说每次来兽潮都会死不少人呢。",
          "Description": "",
          "AvatarIDSetType": "Normal"
        }
      ]
    },
    {
      "ItemID": 284,
      "Name": "海兽",
      "Description": "海兽",
      "Position": "(-2712.694,-1134.018)",
      "Commands": [
        {
          "ItemID": 287,
          "CmdType": "Fungus.Say",
          "AvatarIDInt": 1020,
          "AvatarBindKey": "",
          "StoryText": "这广陵城港口便是通往无尽之海，据说这海里的妖兽都有数万年修为，就连一般的金丹期修士也不敢随意招惹。",
          "Description": "",
          "AvatarIDSetType": "Normal"
        }
      ]
    },
    {
      "ItemID": 280,
      "Name": "New Block",
      "Description": "New Block",
      "Position": "(-2798.694,-1210.018)",
      "Commands": [
        {
          "ItemID": 281,
          "CmdType": "Fungus.Menu",
          "Text": "关于围墙",
          "TargetBlockID": "this:283(围墙)"
        },
        {
          "ItemID": 282,
          "CmdType": "Fungus.Menu",
          "Text": "关于海兽",
          "TargetBlockID": "this:284(海兽)"
        }
      ]
    }
  ],
  "Variables": []
}