{
	"1":{
		"id":1,
		"Type":"放弃竞品",
		"Text":"或许我应该放弃..."
	},
	"2":{
		"id":2,
		"Type":"最低加价",
		"Text":"出价<color=#fbffd4>{lingshi}</color>灵石，慢慢加价可以<color=#fbffd4>炒热</color>拍卖的氛围..."
	},
	"3":{
		"id":3,
		"Type":"略微加价",
		"Text":"出价<color=#fbffd4>{lingshi}</color>灵石。"
	},
	"4":{
		"id":4,
		"Type":"大力加价",
		"Text":"出价<color=#fbffd4>{lingshi}</color>灵石，这样加价或许会让<color=#fbffd4>略感兴趣</color>的人直接<color=#fbffd4>放弃</color>..."
	},
	"5":{
		"id":5,
		"Type":"暴力出价",
		"Text":"出价<color=#fbffd4>{lingshi}</color>灵石，威慑一下其他的竞拍者，这样可以<color=#fbffd4>降低</color>他们的<color=#fbffd4>心理价位</color>..."
	},
	"6":{
		"id":6,
		"Type":"本轮不出",
		"Text":"先观望观望，看看其他人的出价..."
	},
	"7":{
		"id":7,
		"Type":"出言挑衅",
		"Text":"我可以挑衅他人，让他花<color=#fbffd4>更高</color>的价钱参与这次竞价。不过这么做应该会<color=#fbffd4>惹怒</color>拍卖会的主持人..."
	},
	"8":{
		"id":8,
		"Type":"神识威慑",
		"Text":"我可以用神识逼迫他人放弃，不过这么做应该会<color=#fbffd4>惹怒</color>拍卖会的主持人..."
	},
	"9":{
		"id":9,
		"Type":"言语恐吓",
		"Text":"我可以凭境界恐吓他人放弃，不过这么做应该会<color=#fbffd4>惹怒</color>拍卖会的主持人..."
	}
}