{
	"id":1026,
	"Skill_ID":106,
	"Skill_Lv":1,
	"skillEffect":"106.0",
	"Skill_Type":7,
	"name":"青蛇劲1",
	"qingjiaotype":3,
	"seid":[
		4
	],
	"Affix":[],
	"Affix2":[
		1
	],
	"descr":"敌方获得【中毒】*3",
	"TuJiandescr":"敌方获得#c449491【<hy t=中毒 l=2_101_2_1 fhc=#e86524 ul=1>】#n*3",
	"AttackType":[
		1
	],
	"script":"SkillAttack",
	"HP":0,
	"speed":0,
	"icon":0,
	"Skill_DisplayType":0,
	"skill_SameCastNum":[],
	"skill_CastType":[
		1
	],
	"skill_Cast":[
		4
	],
	"Skill_LV":2,
	"typePinJie":3,
	"DF":1,
	"TuJianType":6,
	"Skill_Open":1,
	"Skill_castTime":1,
	"canUseDistMax":30,
	"CD":10000
}